Metadata-Version: 1.1
Name: strategypy
Version: 0.3.0
Summary: A strategy game for Python bots with replaceable front ends
Home-page: https://github.com/davide-ceretti/strategypy
Author: Davide Ceretti
Author-email: dav.ceretti@gmail.com
License: BSD
Keywords: strategypy
Platform: UNKNOWN
Classifier: Development Status :: 2 - Pre-Alpha
Classifier: Intended Audience :: Developers
Classifier: License :: OSI Approved :: BSD License
Classifier: Natural Language :: English
Classifier: Programming Language :: Python :: 2
Classifier: Programming Language :: Python :: 2.7
Classifier: Programming Language :: Python :: 3
Classifier: Programming Language :: Python :: 3.4
